fprime_bootstrap/__init__.py
fprime_bootstrap/__main__.py
fprime_bootstrap/bootstrap_project.py
fprime_bootstrap/clone_project.py
fprime_bootstrap/common.py
fprime_bootstrap/templates/fprime-project-template/.clang-format
fprime_bootstrap/templates/fprime-project-template/.gitignore
fprime_bootstrap/templates/fprime-project-template/CMakeLists.txt-template
fprime_bootstrap/templates/fprime-project-template/CMakePresets.json
fprime_bootstrap/templates/fprime-project-template/README.md-template
fprime_bootstrap/templates/fprime-project-template/requirements.txt-template
fprime_bootstrap/templates/fprime-project-template/settings.ini
fprime_bootstrap/templates/fprime-project-template/lib/README.md
fprime_bootstrap/templates/fprime-project-template/{{FPRIME_PROJECT_NAME}}-template/CMakeLists.txt
fprime_bootstrap/templates/fprime-project-template/{{FPRIME_PROJECT_NAME}}-template/Components/CMakeLists.txt
fprime_bootstrap-1.5.1.dist-info/licenses/LICENSE.txt
fprime_bootstrap-1.5.1.dist-info/licenses/NOTICE.txt
fprime_bootstrap-1.5.1.dist-info/METADATA
fprime_bootstrap-1.5.1.dist-info/WHEEL
fprime_bootstrap-1.5.1.dist-info/entry_points.txt
fprime_bootstrap-1.5.1.dist-info/top_level.txt
fprime_bootstrap-1.5.1.dist-info/RECORD
