Metadata-Version: 2.4
Name: fprime-bootstrap
Version: 1.5.1
Summary: F Prime Flight Software bootstrapping tool
Author-email: Thomas Boyer-Chammard <Thomas.Boyer.Chammard@jpl.nasa.gov>
License:                                  Apache License
Project-URL: Homepage, https://fprime.jpl.nasa.gov
Project-URL: Documentation, https://nasa.github.io/fprime/
Project-URL: Repository, https://github.com/fprime-community/fprime-bootstrap
Keywords: fprime,embedded,nasa,flight,software
Classifier: Development Status :: 5 - Production/Stable
Classifier: Intended Audience :: Developers
Classifier: Operating System :: Unix
Classifier: Operating System :: POSIX
Classifier: Programming Language :: Python
Classifier: Programming Language :: Python :: 3
Classifier: Programming Language :: Python :: 3.8
Classifier: Programming Language :: Python :: 3.9
Classifier: Programming Language :: Python :: 3.10
Classifier: Programming Language :: Python :: 3.11
Classifier: Programming Language :: Python :: 3.12
Classifier: Programming Language :: Python :: Implementation :: CPython
Classifier: Programming Language :: Python :: Implementation :: PyPy
Classifier: License :: OSI Approved :: Apache Software License
Requires-Python: >=3.6
License-File: LICENSE.txt
License-File: NOTICE.txt
Provides-Extra: test
Requires-Dist: pytest; extra == "test"
Provides-Extra: dev
Requires-Dist: black; extra == "dev"
Dynamic: license-file
